imouapi/__init__.py
imouapi/api.py
imouapi/cli.py
imouapi/const.py
imouapi/device.py
imouapi/device_entity.py
imouapi/exceptions.py
imouapi-1.0.14.dist-info/LICENSE
imouapi-1.0.14.dist-info/METADATA
imouapi-1.0.14.dist-info/WHEEL
imouapi-1.0.14.dist-info/RECORD
